netapi/.gitignore
netapi/NetAPIClient.py
netapi/NetAPIGraph.py
netapi/NetViz.py
netapi/__init__.py
dss.netapi_python-0.0.3.dev5.dist-info/METADATA
dss.netapi_python-0.0.3.dev5.dist-info/WHEEL
dss.netapi_python-0.0.3.dev5.dist-info/top_level.txt
dss.netapi_python-0.0.3.dev5.dist-info/RECORD
