Metadata-Version: 2.1
Name: dss.netapi-python
Version: 0.0.3.dev5
Summary: A small Python3-layer for accessing Network-Data via the NetAPI.
Author-email: "Tino Schöllhorn, Pavel Chachev, Olaf Kellermeier, Achim Oberg" <schoellhorn@ifm.uni-mannheim.de>, Pavel Chachev <pavel.dimitrov.chachev@uni-hamburg.de>, Olaf Kellermeier <olaf.kellermeier@uni-hamburg.de>, Achim Oberg <achim.oberg@uni-hamburg.de>
Maintainer-email: Tino Schöllhorn <schoellhorn@ifm.uni-mannheim.de>, Pavel Chachev <pavel.dimitrov.chachev@uni-hamburg.de>
Project-URL: Homepage, https://www.wiso.uni-hamburg.de/fachbereich-sowi/professuren/oberg.html
Classifier: Programming Language :: Python :: 3
Classifier: License :: OSI Approved :: MIT License
Classifier: Operating System :: OS Independent
Requires-Python: >=3.7
Requires-Dist: requests
Requires-Dist: networkx <3.3,>=3.2.1
Requires-Dist: scipy
Requires-Dist: netgraph
